.coveragerc
.gitignore
.travis.yml
MANIFEST.in
README.rst
setup.py
tox.ini
parameterizedtestcase/__init__.py
parameterizedtestcase/tests.py
parameterizedtestcase.egg-info/PKG-INFO
parameterizedtestcase.egg-info/SOURCES.txt
parameterizedtestcase.egg-info/dependency_links.txt
parameterizedtestcase.egg-info/not-zip-safe
parameterizedtestcase.egg-info/top_level.txt