Metadata-Version: 1.1
Name: parameterizedtestcase
Version: 0.1.0
Summary: Parameterized tests for Python's unittest module
Home-page: https://github.com/msabramo/python_unittest_parameterized_test_case
Author: Marc Abramowitz
Author-email: marc@marc-abramowitz.com
License: MIT
Keywords: unittest
Platform: UNKNOWN
Classifier: Programming Language :: Python :: 2
Classifier: Programming Language :: Python :: 2.5
Classifier: Programming Language :: Python :: 2.6
Classifier: Programming Language :: Python :: 2.7
Classifier: Programming Language :: Python :: 3
Classifier: Programming Language :: Python :: 3.0
Classifier: Programming Language :: Python :: 3.1
Classifier: Programming Language :: Python :: 3.2
Classifier: Programming Language :: Python :: 3.3
Classifier: Topic :: Software Development :: Testing
Classifier: Natural Language :: English
Classifier: Intended Audience :: Developers
